ansibleplaybookgrapher/__init__.py
ansibleplaybookgrapher/cli.py
ansibleplaybookgrapher/graph_model.py
ansibleplaybookgrapher/grapher.py
ansibleplaybookgrapher/parser.py
ansibleplaybookgrapher/utils.py
ansibleplaybookgrapher/data/graph.css
ansibleplaybookgrapher/data/highlight-hover.js
ansibleplaybookgrapher/renderer/__init__.py
ansibleplaybookgrapher/renderer/json.py
ansibleplaybookgrapher/renderer/mermaid.py
ansibleplaybookgrapher/renderer/graphviz/__init__.py
ansibleplaybookgrapher/renderer/graphviz/postprocessor.py
ansible_playbook_grapher-2.10.1.dist-info/LICENSE
ansible_playbook_grapher-2.10.1.dist-info/METADATA
ansible_playbook_grapher-2.10.1.dist-info/WHEEL
ansible_playbook_grapher-2.10.1.dist-info/entry_points.txt
ansible_playbook_grapher-2.10.1.dist-info/top_level.txt
ansible_playbook_grapher-2.10.1.dist-info/RECORD
