Metadata-Version: 2.1
Name: ansible-playbook-grapher
Version: 2.10.1
Summary: A command line tool to create a graph representing your Ansible playbook tasks and roles.
Home-page: https://github.com/haidaraM/ansible-playbook-grapher
Download-URL: https://github.com/haidaraM/ansible-playbook-grapher/archive/v2.10.1.tar.gz
Author: HAIDARA Mohamed El Mouctar
Author-email: elmhaidara@gmail.com
License: MIT
Classifier: Development Status :: 5 - Production/Stable
Classifier: Intended Audience :: Developers
Classifier: Intended Audience :: System Administrators
Classifier: License :: OSI Approved :: GNU General Public License v3 (GPLv3)
Classifier: Environment :: Console
Classifier: Topic :: Utilities
Classifier: Programming Language :: Python :: 3.10
Classifier: Programming Language :: Python :: 3.11
Classifier: Programming Language :: Python :: 3.12
License-File: LICENSE
Requires-Dist: ansible-core<2.18.3,>=2.16
Requires-Dist: graphviz<1,>=0.18
Requires-Dist: colour<1
Requires-Dist: lxml<7
Requires-Dist: svg.path<8
